{
    "key": "group_607343290bb12",
    "title": "Vimeo Livestream Embed Code",
    "fields": [
        {
            "key": "field_60734337a834d",
            "label": "Vimeo Live Event Embed Code",
            "name": "vimeo_live_event_embed_code",
            "type": "wysiwyg",
            "instructions": "",
            "required": 0,
            "conditional_logic": 0,
            "wrapper": {
                "width": "",
                "class": "",
                "id": ""
            },
            "default_value": "",
            "tabs": "text",
            "media_upload": 0,
            "toolbar": "full",
            "delay": 0
        }
    ],
    "location": [
        [
            {
                "param": "post_type",
                "operator": "==",
                "value": "post"
            }
        ]
    ],
    "menu_order": 0,
    "position": "normal",
    "style": "default",
    "label_placement": "top",
    "instruction_placement": "label",
    "hide_on_screen": "",
    "active": true,
    "description": "",
    "modified": 1618166838
}